treeprompt/__init__.py
treeprompt/llm_utils.py
treeprompt/stump.py
treeprompt/treeprompt.py
treeprompt-0.0.1.dist-info/METADATA
treeprompt-0.0.1.dist-info/WHEEL
treeprompt-0.0.1.dist-info/top_level.txt
treeprompt-0.0.1.dist-info/RECORD
