Metadata-Version: 2.1
Name: treeprompt
Version: 0.0.1
Summary: Tree prompting
Home-page: https://github.com/csinva/tree-prompt
Author: John X. Morris, Chandan Singh, Yuntian Deng, Sasha Rush
Author-email: 
Classifier: Programming Language :: Python :: 3
Classifier: License :: OSI Approved :: MIT License
Classifier: Operating System :: OS Independent
Requires-Python: >=3.9
Requires-Dist: datasets
Requires-Dist: dict-hash
Requires-Dist: imodels
Requires-Dist: numpy
Requires-Dist: pandas
Requires-Dist: scikit-learn
Requires-Dist: scipy
Requires-Dist: torch
Requires-Dist: tqdm
Requires-Dist: transformers[torch] (>=4.23.1)
